<annotation>
  <folder></folder>
  <filename>cacatuidae-parrot-picture-id1338079211.jpg</filename>
  <source>
    <database>Unknown</database>
    <annotation>Unknown</annotation>
    <image>Unknown</image>
  </source>
  <size>
    <width>612</width>
    <height>408</height>
    <depth></depth>
  </size>
  <segmented>0</segmented>
  <object>
    <name>Bird</name>
    <truncated>0</truncated>
    <occluded>0</occluded>
    <difficult>0</difficult>
    <bndbox>
      <xmin>147.7</xmin>
      <ymin>86.12</ymin>
      <xmax>418.3</xmax>
      <ymax>329.49</ymax>
    </bndbox>
    <attributes>
      <attribute>
        <name>rotation</name>
        <value>0.0</value>
      </attribute>
    </attributes>
  </object>
</annotation>
