<annotation>
  <folder>roseate-spoonbill-picture-id635844752</folder>
  <filename>roseate-spoonbill-picture-id635844752_mirror_solarize.jpg</filename>
  <source>
    <database>Unknown</database>
    <annotation>Unknown</annotation>
    <image>Unknown</image>
  </source>
  <size>
    <width>612</width>
    <height>408</height>
    <depth></depth>
  </size>
  <segmented>0</segmented>
  <object>
    <name>Bird</name>
    <truncated>0</truncated>
    <occluded>0</occluded>
    <difficult>0</difficult>
    <bndbox>
      <xmin>66.01</xmin>
      <ymin>45.49</ymin>
      <xmax>346.67</xmax>
      <ymax>325.31</ymax>
    </bndbox>
    <attributes>
      <attribute>
        <name>rotation</name>
        <value>0.0</value>
      </attribute>
    </attributes>
  </object>
  <object>
    <name>Bird</name>
    <truncated>0</truncated>
    <occluded>0</occluded>
    <difficult>0</difficult>
    <bndbox>
      <xmin>459.73</xmin>
      <ymin>136.97</ymin>
      <xmax>542.67</xmax>
      <ymax>284.0</ymax>
    </bndbox>
    <attributes>
      <attribute>
        <name>rotation</name>
        <value>0.0</value>
      </attribute>
    </attributes>
  </object>
</annotation>
