<annotation>
  <folder>seagulls-picture-id534050814</folder>
  <filename>seagulls-picture-id534050814_mirror_solarize.jpg</filename>
  <source>
    <database>Unknown</database>
    <annotation>Unknown</annotation>
    <image>Unknown</image>
  </source>
  <size>
    <width>612</width>
    <height>340</height>
    <depth></depth>
  </size>
  <segmented>0</segmented>
  <object>
    <name>Bird</name>
    <truncated>0</truncated>
    <occluded>0</occluded>
    <difficult>0</difficult>
    <bndbox>
      <xmin>55.82</xmin>
      <ymin>112.09</ymin>
      <xmax>161.33</xmax>
      <ymax>214.48</ymax>
    </bndbox>
    <attributes>
      <attribute>
        <name>rotation</name>
        <value>0.0</value>
      </attribute>
    </attributes>
  </object>
  <object>
    <name>Bird</name>
    <truncated>0</truncated>
    <occluded>0</occluded>
    <difficult>0</difficult>
    <bndbox>
      <xmin>167.27</xmin>
      <ymin>34.01</ymin>
      <xmax>300.15</xmax>
      <ymax>223.16</ymax>
    </bndbox>
    <attributes>
      <attribute>
        <name>rotation</name>
        <value>0.0</value>
      </attribute>
    </attributes>
  </object>
  <object>
    <name>Bird</name>
    <truncated>0</truncated>
    <occluded>0</occluded>
    <difficult>0</difficult>
    <bndbox>
      <xmin>235.27</xmin>
      <ymin>171.96</ymin>
      <xmax>359.16</xmax>
      <ymax>229.02</ymax>
    </bndbox>
    <attributes>
      <attribute>
        <name>rotation</name>
        <value>0.0</value>
      </attribute>
    </attributes>
  </object>
  <object>
    <name>Bird</name>
    <truncated>0</truncated>
    <occluded>0</occluded>
    <difficult>0</difficult>
    <bndbox>
      <xmin>404.49</xmin>
      <ymin>166.1</ymin>
      <xmax>580.35</xmax>
      <ymax>223.94</ymax>
    </bndbox>
    <attributes>
      <attribute>
        <name>rotation</name>
        <value>0.0</value>
      </attribute>
    </attributes>
  </object>
  <object>
    <name>Bird</name>
    <truncated>0</truncated>
    <occluded>0</occluded>
    <difficult>0</difficult>
    <bndbox>
      <xmin>340.4</xmin>
      <ymin>229.8</ymin>
      <xmax>426.77</xmax>
      <ymax>309.92</ymax>
    </bndbox>
    <attributes>
      <attribute>
        <name>rotation</name>
        <value>0.0</value>
      </attribute>
    </attributes>
  </object>
</annotation>
